[
    {
        "key": "dbln",
        "value": "%7B%2261566559056990%22%3A%22Nqm1irzH%22%2C%2261571124775064%22%3A%22MiM3LqML%22%7D",
        "domain": "facebook.com",
        "path": "/login/device-based/",
        "hostOnly": false,
        "creation": "2024-12-24T03:12:18.806Z",
        "lastAccessed": "2024-12-24T03:12:18.806Z"
    },
    {
        "key": "datr",
        "value": "vNlmZ5T3ZbHvTOHPoEh5Efqs",
        "domain": "facebook.com",
        "path": "/",
        "hostOnly": false,
        "creation": "2024-12-24T03:12:18.806Z",
        "lastAccessed": "2024-12-24T03:12:18.806Z"
    },
    {
        "key": "sb",
        "value": "vNlmZ9U5eiuox1dBWLRYtpTj",
        "domain": "facebook.com",
        "path": "/",
        "hostOnly": false,
        "creation": "2024-12-24T03:12:18.806Z",
        "lastAccessed": "2024-12-24T03:12:18.806Z"
    },
    {
        "key": "vpd",
        "value": "v1%3B772x384x1.875",
        "domain": "facebook.com",
        "path": "/",
        "hostOnly": false,
        "creation": "2024-12-24T03:12:18.806Z",
        "lastAccessed": "2024-12-24T03:12:18.806Z"
    },
    {
        "key": "ps_l",
        "value": "1",
        "domain": "facebook.com",
        "path": "/",
        "hostOnly": false,
        "creation": "2024-12-24T03:12:18.806Z",
        "lastAccessed": "2024-12-24T03:12:18.806Z"
    },
    {
        "key": "ps_n",
        "value": "1",
        "domain": "facebook.com",
        "path": "/",
        "hostOnly": false,
        "creation": "2024-12-24T03:12:18.806Z",
        "lastAccessed": "2024-12-24T03:12:18.806Z"
    },
    {
        "key": "locale",
        "value": "en_US",
        "domain": "facebook.com",
        "path": "/",
        "hostOnly": false,
        "creation": "2024-12-24T03:12:18.806Z",
        "lastAccessed": "2024-12-24T03:12:18.806Z"
    },
    {
        "key": "dpr",
        "value": "1.875",
        "domain": "facebook.com",
        "path": "/",
        "hostOnly": false,
        "creation": "2024-12-24T03:12:18.806Z",
        "lastAccessed": "2024-12-24T03:12:18.806Z"
    },
    {
        "key": "m_pixel_ratio",
        "value": "1.875",
        "domain": "facebook.com",
        "path": "/",
        "hostOnly": false,
        "creation": "2024-12-24T03:12:18.806Z",
        "lastAccessed": "2024-12-24T03:12:18.806Z"
    },
    {
        "key": "c_user",
        "value": "61569782075644",
        "domain": "facebook.com",
        "path": "/",
        "hostOnly": false,
        "creation": "2024-12-24T03:12:18.806Z",
        "lastAccessed": "2024-12-24T03:12:18.806Z"
    },
    {
        "key": "fr",
        "value": "1lLqTNaJ6w0UXGjM6.AWUAnylwE_nVEO0sDvS3hVAfIik.BnaadR..AAA.0.0.BnaiaE.AWUfJUNwlys",
        "domain": "facebook.com",
        "path": "/",
        "hostOnly": false,
        "creation": "2024-12-24T03:12:18.806Z",
        "lastAccessed": "2024-12-24T03:12:18.806Z"
    },
    {
        "key": "xs",
        "value": "19%3A89cPfjlg738xrQ%3A2%3A1735009925%3A-1%3A13303",
        "domain": "facebook.com",
        "path": "/",
        "hostOnly": false,
        "creation": "2024-12-24T03:12:18.806Z",
        "lastAccessed": "2024-12-24T03:12:18.806Z"
    },
    {
        "key": "wd",
        "value": "384x772",
        "domain": "facebook.com",
        "path": "/",
        "hostOnly": false,
        "creation": "2024-12-24T03:12:18.806Z",
        "lastAccessed": "2024-12-24T03:12:18.806Z"
    },
    {
        "key": "fbl_st",
        "value": "100722817%3BT%3A28916832",
        "domain": "facebook.com",
        "path": "/",
        "hostOnly": false,
        "creation": "2024-12-24T03:12:18.806Z",
        "lastAccessed": "2024-12-24T03:12:18.806Z"
    },
    {
        "key": "wl_cbv",
        "value": "v2%3Bclient_version%3A2701%3Btimestamp%3A1735009934",
        "domain": "facebook.com",
        "path": "/",
        "hostOnly": false,
        "creation": "2024-12-24T03:12:18.806Z",
        "lastAccessed": "2024-12-24T03:12:18.806Z"
    }
]
